seidr/README_src.md
seidr/__init__.py
seidr/dev.py
seidr/eval.py
seidr/github.py
seidr/llm.py
seidr/prompt.py
seidr/requirements_src.txt
seidr/templates/commit.txt
seidr/templates/prompts.txt
seidr/templates/template.cpp
seidr/templates/template.java
seidr/templates/template.py
seidr-3.5.0.dist-info/METADATA
seidr-3.5.0.dist-info/WHEEL
seidr-3.5.0.dist-info/RECORD
