Metadata-Version: 2.3
Name: seidr
Version: 3.5.0
Summary: Synthesize Execute Instruct Debug Rank
License: MIT
Author: Vadim Liventsev
Author-email: v.liventsev@tue.nl
Requires-Python: >=3.9,<4.0
Classifier: Intended Audience :: Developers
Classifier: Intended Audience :: Science/Research
Classifier: License :: OSI Approved :: MIT License
Classifier: Programming Language :: Python :: 3
Classifier: Programming Language :: Python :: 3.9
Classifier: Programming Language :: Python :: 3.10
Classifier: Programming Language :: Python :: 3.11
Classifier: Programming Language :: Python :: 3.12
Classifier: Programming Language :: Python :: 3.13
Classifier: Topic :: Software Development :: Compilers
Requires-Dist: anthropic (>=0.29,<1.0)
Requires-Dist: black (>=24.0.0,<25.0.0)
Requires-Dist: fire (<1.0.0)
Requires-Dist: gitpython (>=3.0.0,<4.0.0)
Requires-Dist: jsonlines (>=4.0.0,<5.0.0)
Requires-Dist: langchain (>=0.2.0,<0.3.0)
Requires-Dist: langchain-anthropic (>=0.1,<1.0)
Requires-Dist: langchain-community (>=0.2.6,<0.3.0)
Requires-Dist: langchain-core (>=0.2.10,<0.3.0)
Requires-Dist: langchain-openai (>=0.1.14,<0.2.0)
Requires-Dist: more-itertools (>=10.0.0,<11.0.0)
Requires-Dist: openai (>=1.0.0,<2.0.0)
Requires-Dist: pandas (>=2.0.0)
Requires-Dist: programlib (==12.0.5)
Requires-Dist: psb2 (>=1.1.1,<2.0.0)
Requires-Dist: pytest-codeblocks (>=0.17.0,<0.18.0)
Requires-Dist: tenacity (>=8.0.0,<9.0.0)
Requires-Dist: wandb (>=0.19.0,<0.20.0)
